Metadata-Version: 2.1
Name: jam65st-distributions
Version: 0.1.2
Summary: Gaussian distributions
Author: Jaime Alexander Mendez Medina
Author-email: jam65st@gmail.com
License: MIT
Keywords: udacity AWS machine learning foundations
Classifier: Development Status :: 4 - Beta
Classifier: Environment :: Console :: Curses
Classifier: Intended Audience :: Education
Classifier: License :: OSI Approved :: MIT License
Classifier: Natural Language :: English
Classifier: Programming Language :: Python :: 3
Classifier: Topic :: Education :: Testing
Classifier: Topic :: Scientific/Engineering :: Information Analysis
Classifier: Topic :: Utilities
